{
  "_comment": "Source of truth for the branch protection config applied to `main` on github.com/feastpot/feastpot-platform. Apply with: curl -X PUT -H 'Authorization: Bearer $GITHUB_TOKEN' -H 'Accept: application/vnd.github+json' --data @.github/branch-protection.main.json https://api.github.com/repos/feastpot/feastpot-platform/branches/main/protection",
  "required_status_checks": {
    "strict": true,
    "contexts": [
      "Typecheck",
      "Lint",
      "Prisma validate",
      "Test (coverage ≥ 70%)",
      "Build all apps"
    ]
  },
  "enforce_admins": false,
  "required_pull_request_reviews": {
    "required_approving_review_count": 1,
    "dismiss_stale_reviews": true,
    "require_code_owner_reviews": false
  },
  "restrictions": null,
  "required_linear_history": true,
  "allow_force_pushes": false,
  "allow_deletions": false,
  "required_conversation_resolution": true,
  "block_creations": false
}
